dapclient/__init__.py
dapclient/client.py
dapclient/exceptions.py
dapclient/lib.py
dapclient/model.py
dapclient/net.py
dapclient/cas/__init__.py
dapclient/cas/esgf.py
dapclient/cas/get_cookies.py
dapclient/cas/urs.py
dapclient/handlers/dap.py
dapclient/handlers/lib.py
dapclient/parsers/__init__.py
dapclient/parsers/das.py
dapclient/parsers/dds.py
dapclient/parsers/dmr.py
dapclient/responses/ascii.py
dapclient/responses/das.py
dapclient/responses/dds.py
dapclient/responses/dods.py
dapclient/responses/error.py
dapclient/responses/lib.py
dapclient-1.0.6.dist-info/LICENSE.txt
dapclient-1.0.6.dist-info/METADATA
dapclient-1.0.6.dist-info/WHEEL
dapclient-1.0.6.dist-info/top_level.txt
dapclient-1.0.6.dist-info/RECORD
