Metadata-Version: 2.1
Name: dapclient
Version: 1.0.6
Summary: A client-only fork of pydap using the DAP protocol to access scientific data on the internet.
Author-email: Tim Cera <tim@cerazone.net>
License: BSD-3-Clause
Project-URL: documentation, https://timcera.bitbucket.io/dapclient/docs/index.html#dapclient-documentation
Project-URL: github, https://github.com/timcera/dapclient
Project-URL: bitbucket, https://bitbucket.org/timcera/dapclient/src/main/
Keywords: time-series,cli-app,aggregate,fill,filter
Classifier: Development Status :: 5 - Production/Stable
Classifier: Intended Audience :: Science/Research
Classifier: Intended Audience :: End Users/Desktop
Classifier: Intended Audience :: Developers
Classifier: Environment :: Console
Classifier: License :: OSI Approved :: BSD License
Classifier: Natural Language :: English
Classifier: Operating System :: OS Independent
Classifier: Programming Language :: Python :: 3 :: Only
Classifier: Programming Language :: Python :: 3.8
Classifier: Programming Language :: Python :: 3.9
Classifier: Programming Language :: Python :: 3.10
Classifier: Programming Language :: Python :: 3.11
Classifier: Programming Language :: Python :: 3.12
Classifier: Topic :: Scientific/Engineering :: Information Analysis
Classifier: Topic :: Scientific/Engineering
Classifier: Topic :: Software Development :: Libraries :: Python Modules
Requires-Python: >=3.8
License-File: LICENSE.txt
Requires-Dist: numpy
Requires-Dist: requests
Requires-Dist: webob
Requires-Dist: beautifulsoup4
